Workbook
Name Slicer_category: #N/A
Name Slicer_zone: #N/A

Sheet Raw Data
A2: item_id | B2: category | C2: stock_level | D2: reorder_point | E2: reorder_frequency_days | F2: lead_time_days | G2: daily_demand | H2: storage_location_id | I2: zone | J2: picking_time_seconds | K2: handling_cost_per_unit | L2: unit_price | M2: holding_cost_per_unit_day | N2: stockout_count_last_month | O2: order_fulfillment_rate | P2: total_orders_last_month | Q2: turnover_ratio | R2: layout_efficiency_score | S2: last_restock_date | T2: forecasted_demand_next_7d | U2: KPI_score | V2: Inventory Value | W2: Reorder Status | X2: Stock Status
A3: ITM10000 | B3: Pharma | C3: 283 | D3: 21 | E3: 4 | F3: 4 | G3: 49.85 | H3: L82 | I3: B | J3: 106 | K3: 3.61 | L3: 117.8 | M3: 1.14 | N3: 0 | O3: 0.8 | P3: 700 | Q3: 3.33 | R3: 0.33 | S3: 45339 | T3: 184.37 | U3: 0.556 | V3: =C3*L3 -> 33337.4 | W3: =IF(C3<=D3,"Reorder Required","Sufficient") -> Sufficient | X3: =IF(C3<100,"LOW",IF(C3<250,"Medium","High")) -> High
A4: ITM10001 | B4: Automotive | C4: 301 | D4: 52 | E4: 9 | F4: 6 | G4: 23.34 | H4: L15 | I4: A | J4: 45 | K4: 3.54 | L4: 178.8 | M4: 1.09 | N4: 3 | O4: 0.79 | P4: 736 | Q4: 10.36 | R4: 0.98 | S4: 45566 | T4: 221.94 | U4: 0.723 | V4: =C4*L4 -> 53818.8 | W4: =IF(C4<=D4,"Reorder Required","Sufficient") -> Sufficient | X4: =IF(C4<100,"LOW",IF(C4<250,"Medium","High")) -> High
A5: ITM10002 | B5: Groceries | C5: 132 | D5: 60 | E5: 11 | F5: 8 | G5: 37.69 | H5: L4 | I5: B | J5: 177 | K5: 0.52 | L5: 54.05 | M5: 0.95 | N5: 7 | O5: 0.75 | P5: 814 | Q5: 14.32 | R5: 0.87 | S5: 45389 | T5: 53.85 | U5: 0.68 | V5: =C5*L5 -> 7134.6 | W5: =IF(C5<=D5,"Reorder Required","Sufficient") -> Sufficient | X5: =IF(C5<100,"LOW",IF(C5<250,"Medium","High")) -> Medium
A6: ITM10003 | B6: Automotive | C6: 346 | D6: 46 | E6: 13 | F6: 5 | G6: 33.69 | H6: L95 | I6: A | J6: 39 | K6: 2.64 | L6: 31.1 | M6: 1.9 | N6: 0 | O6: 0.96 | P6: 994 | Q6: 2.08 | R6: 0.29 | S6: 45318 | T6: 92.04 | U6: 0.488 | V6: =C6*L6 -> 10760.6 | W6: =IF(C6<=D6,"Reorder Required","Sufficient") -> Sufficient | X6: =IF(C6<100,"LOW",IF(C6<250,"Medium","High")) -> High
A7: ITM10004 | B7: Automotive | C7: 49 | D7: 55 | E7: 4 | F7: 6 | G7: 49.58 | H7: L36 | I7: D | J7: 35 | K7: 1.4 | L7: 104.97 | M7: 0.63 | N7: 5 | O7: 0.83 | P7: 299 | Q7: 5.65 | R7: 0.96 | S7: 45429 | T7: 194.58 | U7: 0.67 | V7: =C7*L7 -> 5143.53 | W7: =IF(C7<=D7,"Reorder Required","Sufficient") -> Reorder Required | X7: =IF(C7<100,"LOW",IF(C7<250,"Medium","High")) -> LOW
A8: ITM10005 | B8: Apparel | C8: 154 | D8: 62 | E8: 9 | F8: 6 | G8: 35.95 | H8: L32 | I8: A | J8: 94 | K8: 1.96 | L8: 164.12 | M8: 0.66 | N8: 1 | O8: 0.99 | P8: 477 | Q8: 7.61 | R8: 0.95 | S8: 45485 | T8: 180.65 | U8: 0.803 | V8: =C8*L8 -> 25274.48 | W8: =IF(C8<=D8,"Reorder Required","Sufficient") -> Sufficient | X8: =IF(C8<100,"LOW",IF(C8<250,"Medium","High")) -> Medium
A9: ITM10006 | B9: Groceries | C9: 86 | D9: 97 | E9: 6 | F9: 4 | G9: 9.04 | H9: L29 | I9: C | J9: 110 | K9: 4.9 | L9: 134.38 | M9: 0.37 | N9: 8 | O9: 0.88 | P9: 418 | Q9: 4.25 | R9: 0.45 | S9: 45636 | T9: 223.69 | U9: 0.526 | V9: =C9*L9 -> 11556.68 | W9: =IF(C9<=D9,"Reorder Required","Sufficient") -> Reorder Required | X9: =IF(C9<100,"LOW",IF(C9<250,"Medium","High")) -> LOW
A10: ITM10007 | B10: Groceries | C10: 84 | D10: 89 | E10: 13 | F10: 4 | G10: 47.82 | H10: L18 | I10: D | J10: 130 | K10: 0.88 | L10: 131.09 | M10: 1.42 | N10: 7 | O10: 0.74 | P10: 958 | Q10: 11.37 | R10: 0.7 | S10: 45601 | T10: 195.75 | U10: 0.558 | V10: =C10*L10 -> 11011.56 | W10: =IF(C10<=D10,"Reorder Required","Sufficient") -> Reorder Required | X10: =IF(C10<100,"LOW",IF(C10<250,"Medium","High")) -> LOW
A11: ITM10008 | B11: Groceries | C11: 311 | D11: 22 | E11: 4 | F11: 9 | G11: 33.72 | H11: L95 | I11: D | J11: 40 | K11: 3.75 | L11: 13.32 | M11: 0.71 | N11: 8 | O11: 0.86 | P11: 697 | Q11: 10.64 | R11: 0.29 | S11: 45600 | T11: 105.74 | U11: 0.541 | V11: =C11*L11 -> 4142.52 | W11: =IF(C11<=D11,"Reorder Required","Sufficient") -> Sufficient | X11: =IF(C11<100,"LOW",IF(C11<250,"Medium","High")) -> High
A12: ITM10009 | B12: Automotive | C12: 44 | D12: 98 | E12: 9 | F12: 8 | G12: 3.91 | H12: L14 | I12: A | J12: 26 | K12: 1.28 | L12: 70.32 | M12: 1.63 | N12: 8 | O12: 1 | P12: 496 | Q12: 2.65 | R12: 0.27 | S12: 45312 | T12: 154.78 | U12: 0.366 | V12: =C12*L12 -> 3094.08 | W12: =IF(C12<=D12,"Reorder Required","Sufficient") -> Reorder Required | X12: =IF(C12<100,"LOW",IF(C12<250,"Medium","High")) -> LOW
A13: ITM10010 | B13: Pharma | C13: 56 | D13: 63 | E13: 7 | F13: 2 | G13: 33.22 | H13: L87 | I13: B | J13: 107 | K13: 0.53 | L13: 188.5 | M13: 1.95 | N13: 1 | O13: 0.87 | P13: 71 | Q13: 8.97 | R13: 0.6 | S13: 45329 | T13: 266.58 | U13: 0.599 | V13: =C13*L13 -> 10556 | W13: =IF(C13<=D13,"Reorder Required","Sufficient") -> Reorder Required | X13: =IF(C13<100,"LOW",IF(C13<250,"Medium","High")) -> LOW
A14: ITM10011 | B14: Groceries | C14: 20 | D14: 66 | E14: 3 | F14: 7 | G14: 44.27 | H14: L95 | I14: A | J14: 135 | K14: 2.76 | L14: 35.51 | M14: 0.18 | N14: 1 | O14: 0.7 | P14: 599 | Q14: 6.16 | R14: 0.24 | S14: 45388 | T14: 63.97 | U14: 0.632 | V14: =C14*L14 -> 710.2 | W14: =IF(C14<=D14,"Reorder Required","Sufficient") -> Reorder Required | X14: =IF(C14<100,"LOW",IF(C14<250,"Medium","High")) -> LOW
... A3206: ITM13203 | B3206: Apparel | C3206: 377 | D3206: 40 | E3206: 14 | F3206: 3 | G3206: 29.4 | H3206: L48 | I3206: A | J3206: 56 | K3206: 4.92 | L3206: 39.88 | M3206: 1.94 | N3206: 9 | O3206: 0.92 | P3206: 812 | Q3206: 8.74 | R3206: 0.54 | S3206: 45437 | T3206: 193.91 | U3206: 0.435 | V3206: =C3206*L3206 -> 15034.76 | W3206: =IF(C3206<=D3206,"Reorder Required","Sufficient") -> Sufficient | X3206: =IF(C3206<100,"LOW",IF(C3206<250,"Medium","High")) -> High

Sheet Dashboard
A1: Warehouse Inventory Management Dashboard
A7: Total Products 📦 | B7: Total Inventory Value💰 | C7: Reorder Required🔁 | D7: Low Stock Items⚠️
A8: =COUNTA('Raw Data'!A:A)-1 -> 3204 | B8: =SUM('Raw Data'!V:V) -> 89566189 | C8: =COUNTIF('Raw Data'!W:W,"Reorder Required") -> 240 | D8: =COUNTIF('Raw Data'!X:X,"Low") -> 508
A10: Average Daily Demand📈 | B10: Average Fulfillment Rate✅ | C10: Inventory Turnover🚚 | D10: Total Orders🛒
A11: =AVERAGE('Raw Data'!G:G) -> 25.435868 | B11: =AVERAGE('Raw Data'!O:O) -> 0.84973783 | C11: =AVERAGE('Raw Data'!Q:Q) -> 8.1236767 | D11: =SUM('Raw Data'!P:P) -> 1671574

Sheet Pivot Table
A1: Total Stock By Category | H1: Reorder Status
A2: category | B2: Sum of stock_level | H2: Reorder Status | I2: Count of item_id
A3: Apparel | B3: 160416 | H3: Reorder Required | I3: 240
A4: Automotive | B4: 170217 | H4: Sufficient | I4: 2964
A5: Electronics | B5: 172266 | H5: Grand Total | I5: 3204
A6: Groceries | B6: 162997
A7: Pharma | B7: 178331
A8: Grand Total | B8: 844227 | H8: Stock Status Distribution
H9: Stock Status | I9: Count of item_id
A10: Inventory Value by Category | H10: High | I10: 1690
A11: category | B11: Sum of Inventory Value | H11: LOW | I11: 508
A12: Apparel | B12: 16804476 | H12: Medium | I12: 1006
A13: Automotive | B13: 18042426 | H13: Grand Total | I13: 3204
A14: Electronics | B14: 18234366
A15: Groceries | B15: 17342652
A16: Pharma | B16: 19142269 | H16: Order By Warehouse Zone
A17: Grand Total | B17: 89566189 | H17: zone | I17: Sum of total_orders_last_month
H18: A | I18: 418265
A19: Fullfillment Rate by Category | H19: B | I19: 406902
A20: category | B20: Average of order_fulfillment_rate | H20: C | I20: 410740
A21: Apparel | B21: 0.84742301 | H21: D | I21: 435667
A22: Automotive | B22: 0.8518541 | H22: Grand Total | I22: 1671574
A23: Electronics | B23: 0.85132104
A24: Groceries | B24: 0.84768608
A25: Pharma | B25: 0.85015152 | H25: Forecast Demand vs stock
A26: Grand Total | B26: 0.84973783 | H26: category | I26: Average of stock_level | J26: Average of forecasted_demand_next_7d
H27: Apparel | I27: 259.99352 | J27: 155.89658
H28: Automotive | I28: 258.68845 | J28: 153.65733
H29: Electronics | I29: 264.61751 | J29: 157.75899
H30: Groceries | I30: 263.74919 | J30: 153.79966
H31: Pharma | I31: 270.19848 | J31: 150.43808
H32: Grand Total | I32: 263.49157 | J32: 154.28625
